silcar_it_tools/__init__.py
silcar_it_tools/config.py
silcar_it_tools/exe_check.py
silcar_it_tools/packing.py
silcar_it_tools/usb_utils.py
silcar_it_tools/utils.py
silcar_it_tools-0.2.2.dist-info/LICENSE
silcar_it_tools-0.2.2.dist-info/METADATA
silcar_it_tools-0.2.2.dist-info/WHEEL
silcar_it_tools-0.2.2.dist-info/entry_points.txt
silcar_it_tools-0.2.2.dist-info/top_level.txt
silcar_it_tools-0.2.2.dist-info/RECORD
