Metadata-Version: 2.1
Name: silcar_it_tools
Version: 0.2.2
Summary: Basic IT tools used to solve common problems in the Central African Republic.
Author-email: Nate Marti <nate_marti@sil.org>
Project-URL: Homepage, https://gitlab.com/acatbadmin/it-tools
Project-URL: Issues, https://gitlab.com/acatbadmin/it-tools/issues
Classifier: Programming Language :: Python :: 3
Classifier: License :: OSI Approved :: MIT License
Classifier: Operating System :: OS Independent
Requires-Python: >=3.8
License-File: LICENSE
Requires-Dist: pefile
